winmedia_controller/__init__.py
winmedia_controller/media_controller.py
winmedia_controller/test_media_controller.py
winmedia_controller-1.1.dist-info/METADATA
winmedia_controller-1.1.dist-info/WHEEL
winmedia_controller-1.1.dist-info/top_level.txt
winmedia_controller-1.1.dist-info/RECORD
