Metadata-Version: 2.2
Name: winmedia_controller
Version: 1.1
Summary: Windows System Media Controller with Async Support
Home-page: https://github.com/TumGovic/winmedia_controller
Author: TumGovic
Author-email: ygmweuaw2@gmail.com
Keywords: windows,media,controller,async
Classifier: Programming Language :: Python :: 3
Classifier: License :: OSI Approved :: MIT License
Classifier: Operating System :: Microsoft :: Windows
Requires-Python: >=3.7
Requires-Dist: keyboard>=0.13.5
Dynamic: author
Dynamic: author-email
Dynamic: classifier
Dynamic: description
Dynamic: description-content-type
Dynamic: home-page
Dynamic: requires-dist
Dynamic: requires-python
Dynamic: summary
